ofxstatement_dutch-1.7.1-py3.10-nspkg.pth
ofxstatement/plugins/nl/__init__.py
ofxstatement/plugins/nl/asn.py
ofxstatement/plugins/nl/degiro.py
ofxstatement/plugins/nl/icscards.py
ofxstatement/plugins/nl/ing.py
ofxstatement/plugins/nl/knab.py
ofxstatement/plugins/nl/statement.py
ofxstatement_dutch-1.7.1.dist-info/METADATA
ofxstatement_dutch-1.7.1.dist-info/WHEEL
ofxstatement_dutch-1.7.1.dist-info/entry_points.txt
ofxstatement_dutch-1.7.1.dist-info/namespace_packages.txt
ofxstatement_dutch-1.7.1.dist-info/top_level.txt
ofxstatement_dutch-1.7.1.dist-info/zip-safe
ofxstatement_dutch-1.7.1.dist-info/RECORD
